MANIFEST.in
setup.py
asaloader/__init__.py
asaloader/__main__.py
asaloader/alp.py
asaloader/device.py
asaloader/do_prog.py
asaloader/exceptions.py
asaloader/ihex.py
asaloader/loader.py
asaloader/locale.py
locale/asaloader.pot
locale/zh_TW/LC_MESSAGES/asaloader.mo
locale/zh_TW/LC_MESSAGES/asaloader.po
py_asa_loader.egg-info/PKG-INFO
py_asa_loader.egg-info/SOURCES.txt
py_asa_loader.egg-info/dependency_links.txt
py_asa_loader.egg-info/entry_points.txt
py_asa_loader.egg-info/not-zip-safe
py_asa_loader.egg-info/requires.txt
py_asa_loader.egg-info/top_level.txt
utils/l10n.py