Metadata-Version: 1.0
Name: py-asa-loader
Version: 0.4.4
Summary: The program to load binary into ASA series board.
Home-page: https://gitlab.com/MVMC-lab/hervor/py-asa-loader
Author: MVMC-lab
Author-email: ncumvmclab@gmail.com
License: MIT
Platform: UNKNOWN
